setup.py
docs/README.txt
docs/backrefsample.zuml
src/Products/__init__.py
src/Products.ATBackRef.egg-info/PKG-INFO
src/Products.ATBackRef.egg-info/SOURCES.txt
src/Products.ATBackRef.egg-info/dependency_links.txt
src/Products.ATBackRef.egg-info/entry_points.txt
src/Products.ATBackRef.egg-info/namespace_packages.txt
src/Products.ATBackRef.egg-info/not-zip-safe
src/Products.ATBackRef.egg-info/requires.txt
src/Products.ATBackRef.egg-info/top_level.txt
src/Products/ATBackRef/__init__.py
src/Products/ATBackRef/backref.py
src/Products/ATBackRef/configure.zcml
src/Products/ATBackRef/profile/metadata.xml
src/Products/ATBackRef/profile/skins.xml
src/Products/ATBackRef/skins/ATBackRef/backreferencebrowserwidget.pt
src/Products/ATBackRef/skins/ATBackRef/backreferencewidget.pt