Metadata-Version: 1.0
Name: Products.ATBackRef
Version: 2.1
Summary: Back Reference Field/Widget for Plone/Archetypes
Home-page: https://svn.plone.org/svn/archetypes/MoreFieldsAndWidgets/ATBackRef
Author: Phil Auersperg, Jens Klein, et al
Author-email: dev@bluedynamics.com
License: GNU General Public License GPL 2.0
Platform: UNKNOWN
Classifier: Development Status :: 5 - Production/Stable
Classifier: Environment :: Web Environment
Classifier: Framework :: Zope2
Classifier: Framework :: Plone
Classifier: Intended Audience :: Developers
Classifier: License :: OSI Approved :: GNU General Public License (GPL)
Classifier: Topic :: Internet :: WWW/HTTP :: Dynamic Content
Classifier: Topic :: Software Development :: Libraries :: Python Modules
Classifier: Operating System :: OS Independent
Classifier: Programming Language :: Python
